asciidrumming/__init__.py
asciidrumming/_version.py
asciidrumming/assemble.py
asciidrumming/beatpattern.py
asciidrumming/cli.py
asciidrumming/config.py
asciidrumming/parse.py
asciidrumming/sample.py
asciidrumming/voice.py
asciidrumming-0.3.3.dist-info/DESCRIPTION.rst
asciidrumming-0.3.3.dist-info/METADATA
asciidrumming-0.3.3.dist-info/RECORD
asciidrumming-0.3.3.dist-info/WHEEL
asciidrumming-0.3.3.dist-info/entry_points.txt
asciidrumming-0.3.3.dist-info/metadata.json
asciidrumming-0.3.3.dist-info/top_level.txt
