Metadata-Version: 2.0
Name: asciidrumming
Version: 0.3.3
Summary: Ascii-based (drum-)sequencer.
Home-page: http://github.com/isnok/asciidrumming
Author: Konstantin Martini
Author-email: k@tuxcode.org
License: MIT
Platform: UNKNOWN
Requires-Dist: click
Requires-Dist: pydub
Requires-Dist: pyyaml
